mc_remote/__init__.py
mc_remote/block_id.py
mc_remote/connection.py
mc_remote/entity_id.py
mc_remote/event.py
mc_remote/minecraft.py
mc_remote/particle_id.py
mc_remote/util.py
mc_remote/vec3.py
minecraft_remote_api-1214.10.13.dist-info/LICENSE
minecraft_remote_api-1214.10.13.dist-info/METADATA
minecraft_remote_api-1214.10.13.dist-info/WHEEL
minecraft_remote_api-1214.10.13.dist-info/RECORD
