Metadata-Version: 2.3
Name: minecraft-remote-api
Version: 1214.10.13
Summary: Python Client-API for Minecraft Remote or mc-remote
Keywords: minecraft,remote,API,client
Author: Naohiro2g
Author-email: 587586+Naohiro2g@users.noreply.github.com
Requires-Python: >=3.8
Classifier: Programming Language :: Python :: 3.8
Classifier: Programming Language :: Python :: 3.9
Classifier: Programming Language :: Python :: 3.10
Classifier: Programming Language :: Python :: 3.11
Classifier: Programming Language :: Python :: 3.12
Classifier: License :: OSI Approved :: MIT License
Classifier: Operating System :: OS Independent
Project-URL: Documentation, https://github.com/Naohiro2g/minecraft-remote-api/blob/main/README.md
Project-URL: Homepage, https://github.com/Naohiro2g/minecraft-remote-api
Project-URL: Repository, https://github.com/Naohiro2g/minecraft-remote-api
